tfd_py/Config.py
tfd_py/Ouid.py
tfd_py/__init__.py
tfd_py/exceptions.py
tfd_py/api/BasicInformation.py
tfd_py/api/__init__.py
tfd_py/static/__init__.py
tfd_py-0.1.dist-info/licenses/LICENSE.txt
tfd_py-0.1.dist-info/METADATA
tfd_py-0.1.dist-info/WHEEL
tfd_py-0.1.dist-info/top_level.txt
tfd_py-0.1.dist-info/RECORD
