Metadata-Version: 2.4
Name: tfd-py
Version: 0.1
Summary: Async Python library for TFD OpenAPI
Home-page: https://github.com/Paasdag/tfd.py
Author: Dean
License: Creative Commons Attribution-NonCommercial-ShareAlike 4.0 International
Requires-Python: >=3.10
License-File: LICENSE.txt
Requires-Dist: asyncio
Requires-Dist: aiohttp
Requires-Dist: orjson
Dynamic: author
Dynamic: home-page
Dynamic: license
Dynamic: license-file
Dynamic: requires-dist
Dynamic: requires-python
Dynamic: summary
